BlogX/CLI.py
BlogX/common.py
BlogX/config.py
BlogX/themes/BlogX/template.html
BlogX/themes/BlogX/static/blog-reader.apk
BlogX/themes/BlogX/static/css/jquery.fancybox.min.css
BlogX/themes/BlogX/static/css/pygments.css
BlogX/themes/BlogX/static/css/style.css
BlogX/themes/BlogX/static/css/toastr.min.css
BlogX/themes/BlogX/static/js/clipboard.min.js
BlogX/themes/BlogX/static/js/copy-tex.min.js
BlogX/themes/BlogX/static/js/jquery.fancybox.min.js
BlogX/themes/BlogX/static/js/jquery.min.js
BlogX/themes/BlogX/static/js/main.js
BlogX/themes/BlogX/static/js/protect-content.js
BlogX/themes/BlogX/static/js/toastr.js.map
BlogX/themes/BlogX/static/js/toastr.min.js
BlogX-0.3.3.dist-info/LICENSE
BlogX-0.3.3.dist-info/METADATA
BlogX-0.3.3.dist-info/WHEEL
BlogX-0.3.3.dist-info/entry_points.txt
BlogX-0.3.3.dist-info/top_level.txt
BlogX-0.3.3.dist-info/RECORD
